{ 
    "locations":[
        { 
            "Id":"A",
            "POS":"3,5"
        },
        {
            "Id":"B",
            "POS":"11,2"
        },
        {
            "Id":"C",
            "POS":"16,8"
        },
        {
            "Id":"D",
            "POS":"16,17"
        },
        {
            "Id":"E",
            "POS":"10,19"
        },
        {
            "Id":"F",
            "POS":"5,11"
        },
        {
            "Id":"G",
            "POS":"19,11"
        }
    ]  
}
